msrest/__init__.py
msrest/async_client.py
msrest/async_paging.py
msrest/authentication.py
msrest/configuration.py
msrest/exceptions.py
msrest/http_logger.py
msrest/paging.py
msrest/py.typed
msrest/serialization.py
msrest/service_client.py
msrest/version.py
msrest/pipeline/__init__.py
msrest/pipeline/aiohttp.py
msrest/pipeline/async_abc.py
msrest/pipeline/async_requests.py
msrest/pipeline/requests.py
msrest/pipeline/universal.py
msrest/polling/__init__.py
msrest/polling/async_poller.py
msrest/polling/poller.py
msrest/universal_http/__init__.py
msrest/universal_http/aiohttp.py
msrest/universal_http/async_abc.py
msrest/universal_http/async_requests.py
msrest/universal_http/requests.py
msrest-0.7.0.dist-info/LICENSE.md
msrest-0.7.0.dist-info/METADATA
msrest-0.7.0.dist-info/WHEEL
msrest-0.7.0.dist-info/top_level.txt
msrest-0.7.0.dist-info/RECORD
