Metadata-Version: 2.1
Name: msrest
Version: 0.7.0
Summary: AutoRest swagger generator Python client runtime.
Home-page: https://github.com/Azure/msrest-for-python
Author: Microsoft Corporation
License: MIT License
Platform: UNKNOWN
Classifier: Development Status :: 4 - Beta
Classifier: Programming Language :: Python
Classifier: Programming Language :: Python :: 2
Classifier: Programming Language :: Python :: 2.7
Classifier: Programming Language :: Python :: 3
Classifier: Programming Language :: Python :: 3.6
Classifier: Programming Language :: Python :: 3.7
Classifier: Programming Language :: Python :: 3.8
Classifier: Programming Language :: Python :: 3.9
Classifier: Programming Language :: Python :: 3.10
Classifier: License :: OSI Approved :: MIT License
Classifier: Topic :: Software Development
Provides-Extra: async
